{
  "image_name": "img220.jpg",
  "center": {
    "x": 158.82,
    "y": 158.82
  },
  "gauge_radius_min": 124.01754271069879,
  "gauge_radius_max": 122.28704673840153,
  "min": {
    "keypoint": {
      "x": 54.12,
      "y": 225.29
    },
    "ground_truth": 3.0,
    "crop": {
      "x1": 0,
      "y1": 169,
      "x2": 110,
      "y2": 281,
      "width": 110,
      "height": 112,
      "offset_x": 0,
      "offset_y": 169
    },
    "ocr_detections_count": 1,
    "numeric_candidates_count": 1,
    "all_detections": [
      {
        "text": "10",
        "confidence": 0.9958562850952148,
        "bbox": [
          [
            69.66666666666667,
            2.3333333333333335
          ],
          [
            94.33333333333333,
            2.3333333333333335
          ],
          [
            94.33333333333333,
            24.0
          ],
          [
            69.66666666666667,
            24.0
          ]
        ],
        "bbox_center": [
          82.0,
          13.166666666666666
        ]
      }
    ],
    "numeric_candidates": [
      {
        "text": "10",
        "confidence": 0.9958562850952148,
        "bbox_center": [
          82.0,
          13.166666666666666
        ]
      }
    ],
    "selected_candidate": {
      "text": "10",
      "value": 10.0,
      "confidence": 0.9958562850952148,
      "center_x": 82.0,
      "center_y": 182.16666666666666,
      "distance_to_keypoint": 51.35091311532618
    }
  },
  "max": {
    "keypoint": {
      "x": 245.29,
      "y": 245.29
    },
    "ground_truth": 100.0,
    "crop": {
      "x1": 189,
      "y1": 189,
      "x2": 301,
      "y2": 301,
      "width": 112,
      "height": 112,
      "offset_x": 189,
      "offset_y": 189
    },
    "ocr_detections_count": 2,
    "numeric_candidates_count": 1,
    "all_detections": [
      {
        "text": "JO",
        "confidence": 0.635021984577179,
        "bbox": [
          [
            38.666666666666664,
            0.0
          ],
          [
            60.666666666666664,
            0.0
          ],
          [
            60.666666666666664,
            7.666666666666667
          ],
          [
            38.666666666666664,
            7.666666666666667
          ]
        ],
        "bbox_center": [
          49.666666666666664,
          3.8333333333333335
        ]
      },
      {
        "text": "100",
        "confidence": 0.9991700053215027,
        "bbox": [
          [
            13.0,
            13.333333333333334
          ],
          [
            47.0,
            13.333333333333334
          ],
          [
            47.0,
            36.0
          ],
          [
            13.0,
            36.0
          ]
        ],
        "bbox_center": [
          30.0,
          24.666666666666668
        ]
      }
    ],
    "numeric_candidates": [
      {
        "text": "100",
        "confidence": 0.9991700053215027,
        "bbox_center": [
          30.0,
          24.666666666666668
        ]
      }
    ],
    "selected_candidate": {
      "text": "100",
      "value": 100.0,
      "confidence": 0.9991700053215027,
      "center_x": 219.0,
      "center_y": 213.66666666666666,
      "distance_to_keypoint": 41.124193744207446
    }
  }
}