{
  "image_name": "img48.jpg",
  "center": {
    "x": 154.03,
    "y": 159.69
  },
  "gauge_radius_min": 97.010995768521,
  "gauge_radius_max": 99.59071944714528,
  "min": {
    "keypoint": {
      "x": 82.36,
      "y": 225.07
    },
    "ground_truth": 0.0,
    "crop": {
      "x1": 38,
      "y1": 181,
      "x2": 126,
      "y2": 269,
      "width": 88,
      "height": 88,
      "offset_x": 38,
      "offset_y": 181
    },
    "ocr_detections_count": 2,
    "numeric_candidates_count": 1,
    "all_detections": [
      {
        "text": "1",
        "confidence": 0.7439117431640625,
        "bbox": [
          [
            33.333333333333336,
            48.333333333333336
          ],
          [
            39.333333333333336,
            48.333333333333336
          ],
          [
            39.333333333333336,
            56.0
          ],
          [
            33.333333333333336,
            56.0
          ]
        ],
        "bbox_center": [
          36.333333333333336,
          52.16666666666667
        ]
      },
      {
        "text": "HV",
        "confidence": 0.6145695447921753,
        "bbox": [
          [
            65.0,
            56.666666666666664
          ],
          [
            87.33333333333333,
            55.333333333333336
          ],
          [
            87.66666666666667,
            78.0
          ],
          [
            66.33333333333333,
            79.33333333333333
          ]
        ],
        "bbox_center": [
          76.58333333333333,
          67.33333333333333
        ]
      }
    ],
    "numeric_candidates": [
      {
        "text": "1",
        "confidence": 0.7439117431640625,
        "bbox_center": [
          36.333333333333336,
          52.16666666666667
        ]
      }
    ],
    "selected_candidate": {
      "text": "1",
      "value": 1.0,
      "confidence": 0.7439117431640625,
      "center_x": 74.33333333333334,
      "center_y": 233.16666666666669,
      "distance_to_keypoint": 11.40102578230964
    }
  },
  "max": {
    "keypoint": {
      "x": 225.7,
      "y": 228.84
    },
    "ground_truth": 10.0,
    "crop": {
      "x1": 180,
      "y1": 183,
      "x2": 270,
      "y2": 273,
      "width": 90,
      "height": 90,
      "offset_x": 180,
      "offset_y": 183
    },
    "ocr_detections_count": 2,
    "numeric_candidates_count": 2,
    "all_detections": [
      {
        "text": "40",
        "confidence": 0.9297512173652649,
        "bbox": [
          [
            15.0,
            8.0
          ],
          [
            28.0,
            8.0
          ],
          [
            28.0,
            19.0
          ],
          [
            15.0,
            19.0
          ]
        ],
        "bbox_center": [
          21.5,
          13.5
        ]
      },
      {
        "text": "10",
        "confidence": 0.9972761869430542,
        "bbox": [
          [
            44.666666666666664,
            50.666666666666664
          ],
          [
            60.333333333333336,
            50.666666666666664
          ],
          [
            60.333333333333336,
            67.0
          ],
          [
            44.666666666666664,
            67.0
          ]
        ],
        "bbox_center": [
          52.5,
          58.83333333333333
        ]
      }
    ],
    "numeric_candidates": [
      {
        "text": "40",
        "confidence": 0.9297512173652649,
        "bbox_center": [
          21.5,
          13.5
        ]
      },
      {
        "text": "10",
        "confidence": 0.9972761869430542,
        "bbox_center": [
          52.5,
          58.83333333333333
        ]
      }
    ],
    "selected_candidate": {
      "text": "10",
      "value": 10.0,
      "confidence": 0.9972761869430542,
      "center_x": 232.5,
      "center_y": 241.83333333333331,
      "distance_to_keypoint": 14.665152952189441
    }
  }
}