{
  "image_name": "img67.jpg",
  "center": {
    "x": 162.2,
    "y": 159.69
  },
  "gauge_radius_min": 91.6853428853271,
  "gauge_radius_max": 100.92005796668965,
  "min": {
    "keypoint": {
      "x": 94.3,
      "y": 221.3
    },
    "ground_truth": 0.0,
    "crop": {
      "x1": 52,
      "y1": 179,
      "x2": 136,
      "y2": 263,
      "width": 84,
      "height": 84,
      "offset_x": 52,
      "offset_y": 179
    },
    "ocr_detections_count": 0,
    "numeric_candidates_count": 0,
    "all_detections": [],
    "numeric_candidates": [],
    "selected_candidate": null
  },
  "max": {
    "keypoint": {
      "x": 234.5,
      "y": 230.1
    },
    "ground_truth": 700.0,
    "crop": {
      "x1": 188,
      "y1": 184,
      "x2": 280,
      "y2": 276,
      "width": 92,
      "height": 92,
      "offset_x": 188,
      "offset_y": 184
    },
    "ocr_detections_count": 3,
    "numeric_candidates_count": 2,
    "all_detections": [
      {
        "text": "0000",
        "confidence": 0.9933561086654663,
        "bbox": [
          [
            2.0,
            6.0
          ],
          [
            39.333333333333336,
            8.0
          ],
          [
            38.333333333333336,
            27.0
          ],
          [
            1.0,
            25.333333333333332
          ]
        ],
        "bbox_center": [
          20.166666666666668,
          16.583333333333332
        ]
      },
      {
        "text": "KL.1.6",
        "confidence": 0.8185861706733704,
        "bbox": [
          [
            15.666666666666666,
            46.666666666666664
          ],
          [
            43.666666666666664,
            48.333333333333336
          ],
          [
            43.0,
            60.333333333333336
          ],
          [
            14.666666666666666,
            58.666666666666664
          ]
        ],
        "bbox_center": [
          29.25,
          53.5
        ]
      },
      {
        "text": "700",
        "confidence": 0.9485985636711121,
        "bbox": [
          [
            42.333333333333336,
            44.666666666666664
          ],
          [
            68.66666666666667,
            41.333333333333336
          ],
          [
            71.66666666666667,
            65.66666666666667
          ],
          [
            45.333333333333336,
            69.0
          ]
        ],
        "bbox_center": [
          57.0,
          55.16666666666667
        ]
      }
    ],
    "numeric_candidates": [
      {
        "text": "0000",
        "confidence": 0.9933561086654663,
        "bbox_center": [
          20.166666666666668,
          16.583333333333332
        ]
      },
      {
        "text": "700",
        "confidence": 0.9485985636711121,
        "bbox_center": [
          57.0,
          55.16666666666667
        ]
      }
    ],
    "selected_candidate": {
      "text": "700",
      "value": 700.0,
      "confidence": 0.9485985636711121,
      "center_x": 245.0,
      "center_y": 239.16666666666669,
      "distance_to_keypoint": 13.87279512010629
    }
  }
}