{
  "image_name": "img73.jpg",
  "center": {
    "x": 160.31,
    "y": 158.43
  },
  "gauge_radius_min": 134.69750740084243,
  "gauge_radius_max": 133.4342504756556,
  "min": {
    "keypoint": {
      "x": 64.75,
      "y": 253.36
    },
    "ground_truth": 0.0,
    "crop": {
      "x1": 3,
      "y1": 192,
      "x2": 125,
      "y2": 314,
      "width": 122,
      "height": 122,
      "offset_x": 3,
      "offset_y": 192
    },
    "ocr_detections_count": 1,
    "numeric_candidates_count": 1,
    "all_detections": [
      {
        "text": "0",
        "confidence": 0.592652440071106,
        "bbox": [
          [
            86.33333333333333,
            7.333333333333333
          ],
          [
            103.0,
            7.333333333333333
          ],
          [
            103.0,
            33.333333333333336
          ],
          [
            86.33333333333333,
            33.333333333333336
          ]
        ],
        "bbox_center": [
          94.66666666666666,
          20.333333333333336
        ]
      }
    ],
    "numeric_candidates": [
      {
        "text": "0",
        "confidence": 0.592652440071106,
        "bbox_center": [
          94.66666666666666,
          20.333333333333336
        ]
      }
    ],
    "selected_candidate": {
      "text": "0",
      "value": 0.0,
      "confidence": 0.592652440071106,
      "center_x": 97.66666666666666,
      "center_y": 212.33333333333334,
      "distance_to_keypoint": 52.599375682817964
    }
  },
  "max": {
    "keypoint": {
      "x": 251.47,
      "y": 255.87
    },
    "ground_truth": 80.0,
    "crop": {
      "x1": 190,
      "y1": 194,
      "x2": 312,
      "y2": 316,
      "width": 122,
      "height": 122,
      "offset_x": 190,
      "offset_y": 194
    },
    "ocr_detections_count": 0,
    "numeric_candidates_count": 0,
    "all_detections": [],
    "numeric_candidates": [],
    "selected_candidate": null
  }
}