{
  "image_name": "img14.jpg",
  "center": {
    "x": 159.06,
    "y": 152.14
  },
  "gauge_radius_min": 109.36476397816622,
  "gauge_radius_max": 110.89158038372437,
  "min": {
    "keypoint": {
      "x": 81.1,
      "y": 228.84
    },
    "ground_truth": 0.0,
    "crop": {
      "x1": 31,
      "y1": 178,
      "x2": 131,
      "y2": 278,
      "width": 100,
      "height": 100,
      "offset_x": 31,
      "offset_y": 178
    },
    "ocr_detections_count": 1,
    "numeric_candidates_count": 1,
    "all_detections": [
      {
        "text": "0",
        "confidence": 0.5566276897521085,
        "bbox": [
          [
            23.143715148077344,
            0.6756757214787624
          ],
          [
            36.817748892125444,
            -3.660952042722567
          ],
          [
            50.85628485192266,
            39.65765761185457
          ],
          [
            37.182251107874556,
            44.327618709389235
          ]
        ],
        "bbox_center": [
          37.0,
          20.25
        ]
      }
    ],
    "numeric_candidates": [
      {
        "text": "0",
        "confidence": 0.5566276897521085,
        "bbox_center": [
          37.0,
          20.25
        ]
      }
    ],
    "selected_candidate": {
      "text": "0",
      "value": 0.0,
      "confidence": 0.5566276897521085,
      "center_x": 68.0,
      "center_y": 198.25,
      "distance_to_keypoint": 33.276990549026515
    }
  },
  "max": {
    "keypoint": {
      "x": 232.61,
      "y": 235.13
    },
    "ground_truth": 120.0,
    "crop": {
      "x1": 182,
      "y1": 185,
      "x2": 282,
      "y2": 285,
      "width": 100,
      "height": 100,
      "offset_x": 182,
      "offset_y": 185
    },
    "ocr_detections_count": 3,
    "numeric_candidates_count": 2,
    "all_detections": [
      {
        "text": "120",
        "confidence": 0.9949734807014465,
        "bbox": [
          [
            5.666666666666667,
            15.0
          ],
          [
            39.666666666666664,
            15.0
          ],
          [
            39.666666666666664,
            37.0
          ],
          [
            5.666666666666667,
            37.0
          ]
        ],
        "bbox_center": [
          22.666666666666664,
          26.0
        ]
      },
      {
        "text": "56",
        "confidence": 0.9031349133030715,
        "bbox": [
          [
            0.0,
            36.333333333333336
          ],
          [
            13.0,
            36.333333333333336
          ],
          [
            13.0,
            50.333333333333336
          ],
          [
            0.0,
            50.333333333333336
          ]
        ],
        "bbox_center": [
          6.5,
          43.333333333333336
        ]
      },
      {
        "text": "Min",
        "confidence": 0.34323587571649056,
        "bbox": [
          [
            0.0,
            53.333333333333336
          ],
          [
            28.666666666666668,
            53.333333333333336
          ],
          [
            28.666666666666668,
            70.0
          ],
          [
            0.0,
            70.0
          ]
        ],
        "bbox_center": [
          14.333333333333334,
          61.66666666666667
        ]
      }
    ],
    "numeric_candidates": [
      {
        "text": "120",
        "confidence": 0.9949734807014465,
        "bbox_center": [
          22.666666666666664,
          26.0
        ]
      },
      {
        "text": "56",
        "confidence": 0.9031349133030715,
        "bbox_center": [
          6.5,
          43.333333333333336
        ]
      }
    ],
    "selected_candidate": {
      "text": "120",
      "value": 120.0,
      "confidence": 0.9949734807014465,
      "center_x": 204.66666666666666,
      "center_y": 211.0,
      "distance_to_keypoint": 36.92000511616675
    }
  }
}