{
  "image_name": "img258.jpg",
  "center": {
    "x": 157.65,
    "y": 161.76
  },
  "gauge_radius_min": 105.8368107040268,
  "gauge_radius_max": 108.40336710637727,
  "min": {
    "keypoint": {
      "x": 91.18,
      "y": 244.12
    },
    "ground_truth": 0.0,
    "crop": {
      "x1": 43,
      "y1": 196,
      "x2": 139,
      "y2": 292,
      "width": 96,
      "height": 96,
      "offset_x": 43,
      "offset_y": 196
    },
    "ocr_detections_count": 3,
    "numeric_candidates_count": 2,
    "all_detections": [
      {
        "text": "2",
        "confidence": 0.9980640253709225,
        "bbox": [
          [
            1.0,
            15.0
          ],
          [
            21.0,
            15.0
          ],
          [
            21.0,
            35.666666666666664
          ],
          [
            1.0,
            35.666666666666664
          ]
        ],
        "bbox_center": [
          11.0,
          25.333333333333332
        ]
      },
      {
        "text": "6",
        "confidence": 0.49582120843192357,
        "bbox": [
          [
            91.0,
            85.0
          ],
          [
            95.66666666666667,
            85.0
          ],
          [
            95.66666666666667,
            95.0
          ],
          [
            91.0,
            95.0
          ]
        ],
        "bbox_center": [
          93.33333333333334,
          90.0
        ]
      },
      {
        "text": "ABS Case;",
        "confidence": 0.7906177542731028,
        "bbox": [
          [
            50.821815656471635,
            65.00955227185285
          ],
          [
            93.65588778776068,
            84.47742234806545
          ],
          [
            86.51151767686169,
            99.32378106148047
          ],
          [
            43.67744554557266,
            79.52257765193455
          ]
        ],
        "bbox_center": [
          68.66666666666666,
          82.08333333333333
        ]
      }
    ],
    "numeric_candidates": [
      {
        "text": "2",
        "confidence": 0.9980640253709225,
        "bbox_center": [
          11.0,
          25.333333333333332
        ]
      },
      {
        "text": "6",
        "confidence": 0.49582120843192357,
        "bbox_center": [
          93.33333333333334,
          90.0
        ]
      }
    ],
    "selected_candidate": {
      "text": "2",
      "value": 2.0,
      "confidence": 0.9980640253709225,
      "center_x": 54.0,
      "center_y": 221.33333333333334,
      "distance_to_keypoint": 43.6071620009578
    }
  },
  "max": {
    "keypoint": {
      "x": 239.41,
      "y": 232.94
    },
    "ground_truth": 200.0,
    "crop": {
      "x1": 190,
      "y1": 183,
      "x2": 288,
      "y2": 281,
      "width": 98,
      "height": 98,
      "offset_x": 190,
      "offset_y": 183
    },
    "ocr_detections_count": 4,
    "numeric_candidates_count": 3,
    "all_detections": [
      {
        "text": "1400",
        "confidence": 0.9997630715370178,
        "bbox": [
          [
            0.0,
            12.0
          ],
          [
            34.333333333333336,
            12.0
          ],
          [
            34.333333333333336,
            36.333333333333336
          ],
          [
            0.0,
            36.333333333333336
          ]
        ],
        "bbox_center": [
          17.166666666666668,
          24.166666666666668
        ]
      },
      {
        "text": "2",
        "confidence": 0.8219162081400668,
        "bbox": [
          [
            82.0690058931513,
            -3.3157891346986026
          ],
          [
            99.26647558051452,
            -1.547914598406642
          ],
          [
            95.9309941068487,
            25.649122468031937
          ],
          [
            78.73352441948548,
            23.547914598406646
          ]
        ],
        "bbox_center": [
          89.0,
          11.083333333333334
        ]
      },
      {
        "text": "200",
        "confidence": 0.9993310459745591,
        "bbox": [
          [
            45.424676179113014,
            63.64021807364804
          ],
          [
            66.83594519984634,
            43.71446097623927
          ],
          [
            80.90865715422032,
            62.02644859301862
          ],
          [
            59.49738813348699,
            81.95220569042739
          ]
        ],
        "bbox_center": [
          63.166666666666664,
          62.83333333333333
        ]
      },
      {
        "text": "Socket",
        "confidence": 0.9140297183541418,
        "bbox": [
          [
            19.223932940882875,
            87.3358994113243
          ],
          [
            50.88696820457582,
            70.41542934629707
          ],
          [
            57.77606705911713,
            85.6641005886757
          ],
          [
            26.113031795424178,
            102.58457065370294
          ]
        ],
        "bbox_center": [
          38.5,
          86.5
        ]
      }
    ],
    "numeric_candidates": [
      {
        "text": "1400",
        "confidence": 0.9997630715370178,
        "bbox_center": [
          17.166666666666668,
          24.166666666666668
        ]
      },
      {
        "text": "2",
        "confidence": 0.8219162081400668,
        "bbox_center": [
          89.0,
          11.083333333333334
        ]
      },
      {
        "text": "200",
        "confidence": 0.9993310459745591,
        "bbox_center": [
          63.166666666666664,
          62.83333333333333
        ]
      }
    ],
    "selected_candidate": {
      "text": "200",
      "value": 200.0,
      "confidence": 0.9993310459745591,
      "center_x": 253.16666666666666,
      "center_y": 245.83333333333331,
      "distance_to_keypoint": 18.85428127036991
    }
  }
}