{
  "image_name": "img250.jpg",
  "center": {
    "x": 161.18,
    "y": 164.12
  },
  "gauge_radius_min": 114.69271118950847,
  "gauge_radius_max": 111.57427122773422,
  "min": {
    "keypoint": {
      "x": 98.24,
      "y": 260.0
    },
    "ground_truth": 0.0,
    "crop": {
      "x1": 46,
      "y1": 208,
      "x2": 150,
      "y2": 312,
      "width": 104,
      "height": 104,
      "offset_x": 46,
      "offset_y": 208
    },
    "ocr_detections_count": 1,
    "numeric_candidates_count": 1,
    "all_detections": [
      {
        "text": "0",
        "confidence": 0.9987247482187378,
        "bbox": [
          [
            49.333333333333336,
            58.666666666666664
          ],
          [
            59.333333333333336,
            58.666666666666664
          ],
          [
            59.333333333333336,
            70.0
          ],
          [
            49.333333333333336,
            70.0
          ]
        ],
        "bbox_center": [
          54.333333333333336,
          64.33333333333333
        ]
      }
    ],
    "numeric_candidates": [
      {
        "text": "0",
        "confidence": 0.9987247482187378,
        "bbox_center": [
          54.333333333333336,
          64.33333333333333
        ]
      }
    ],
    "selected_candidate": {
      "text": "0",
      "value": 0.0,
      "confidence": 0.9987247482187378,
      "center_x": 100.33333333333334,
      "center_y": 272.3333333333333,
      "distance_to_keypoint": 12.5097224411877
    }
  },
  "max": {
    "keypoint": {
      "x": 257.06,
      "y": 221.18
    },
    "ground_truth": 300.0,
    "crop": {
      "x1": 206,
      "y1": 170,
      "x2": 308,
      "y2": 272,
      "width": 102,
      "height": 102,
      "offset_x": 206,
      "offset_y": 170
    },
    "ocr_detections_count": 2,
    "numeric_candidates_count": 2,
    "all_detections": [
      {
        "text": "20 _",
        "confidence": 0.5949593782424927,
        "bbox": [
          [
            18.333333333333332,
            6.333333333333333
          ],
          [
            41.0,
            6.333333333333333
          ],
          [
            41.0,
            26.333333333333332
          ],
          [
            18.333333333333332,
            26.333333333333332
          ]
        ],
        "bbox_center": [
          29.666666666666664,
          16.333333333333332
        ]
      },
      {
        "text": "300",
        "confidence": 0.9999624213631827,
        "bbox": [
          [
            45.92388531395846,
            53.809713284896155
          ],
          [
            75.43455876171845,
            47.27309529814017
          ],
          [
            78.7427813527082,
            65.85695338177051
          ],
          [
            49.232107904948215,
            72.72690470185982
          ]
        ],
        "bbox_center": [
          62.33333333333333,
          59.916666666666664
        ]
      }
    ],
    "numeric_candidates": [
      {
        "text": "20 _",
        "confidence": 0.5949593782424927,
        "bbox_center": [
          29.666666666666664,
          16.333333333333332
        ]
      },
      {
        "text": "300",
        "confidence": 0.9999624213631827,
        "bbox_center": [
          62.33333333333333,
          59.916666666666664
        ]
      }
    ],
    "selected_candidate": {
      "text": "300",
      "value": 300.0,
      "confidence": 0.9999624213631827,
      "center_x": 268.3333333333333,
      "center_y": 229.91666666666666,
      "distance_to_keypoint": 14.262446805821508
    }
  }
}