{
  "image_name": "img64.jpg",
  "center": {
    "x": 162.2,
    "y": 157.17
  },
  "gauge_radius_min": 105.04917753128771,
  "gauge_radius_max": 99.97184003508188,
  "min": {
    "keypoint": {
      "x": 84.24,
      "y": 227.58
    },
    "ground_truth": 0.0,
    "crop": {
      "x1": 36,
      "y1": 179,
      "x2": 132,
      "y2": 275,
      "width": 96,
      "height": 96,
      "offset_x": 36,
      "offset_y": 179
    },
    "ocr_detections_count": 1,
    "numeric_candidates_count": 1,
    "all_detections": [
      {
        "text": "0",
        "confidence": 0.8537003993988037,
        "bbox": [
          [
            28.666666666666668,
            56.333333333333336
          ],
          [
            40.0,
            56.333333333333336
          ],
          [
            40.0,
            72.0
          ],
          [
            28.666666666666668,
            72.0
          ]
        ],
        "bbox_center": [
          34.333333333333336,
          64.16666666666667
        ]
      }
    ],
    "numeric_candidates": [
      {
        "text": "0",
        "confidence": 0.8537003993988037,
        "bbox_center": [
          34.333333333333336,
          64.16666666666667
        ]
      }
    ],
    "selected_candidate": {
      "text": "0",
      "value": 0.0,
      "confidence": 0.8537003993988037,
      "center_x": 70.33333333333334,
      "center_y": 243.16666666666669,
      "distance_to_keypoint": 20.88874231627063
    }
  },
  "max": {
    "keypoint": {
      "x": 223.18,
      "y": 236.39
    },
    "ground_truth": 140.0,
    "crop": {
      "x1": 178,
      "y1": 191,
      "x2": 268,
      "y2": 281,
      "width": 90,
      "height": 90,
      "offset_x": 178,
      "offset_y": 191
    },
    "ocr_detections_count": 2,
    "numeric_candidates_count": 2,
    "all_detections": [
      {
        "text": "20",
        "confidence": 0.9993477165699005,
        "bbox": [
          [
            19.333333333333332,
            7.333333333333333
          ],
          [
            41.0,
            7.333333333333333
          ],
          [
            41.0,
            26.0
          ],
          [
            19.333333333333332,
            26.0
          ]
        ],
        "bbox_center": [
          30.166666666666664,
          16.666666666666668
        ]
      },
      {
        "text": "140",
        "confidence": 0.9951856732368469,
        "bbox": [
          [
            47.0,
            54.333333333333336
          ],
          [
            71.66666666666667,
            54.666666666666664
          ],
          [
            71.33333333333333,
            72.0
          ],
          [
            46.666666666666664,
            71.66666666666667
          ]
        ],
        "bbox_center": [
          59.166666666666664,
          63.16666666666667
        ]
      }
    ],
    "numeric_candidates": [
      {
        "text": "20",
        "confidence": 0.9993477165699005,
        "bbox_center": [
          30.166666666666664,
          16.666666666666668
        ]
      },
      {
        "text": "140",
        "confidence": 0.9951856732368469,
        "bbox_center": [
          59.166666666666664,
          63.16666666666667
        ]
      }
    ],
    "selected_candidate": {
      "text": "140",
      "value": 140.0,
      "confidence": 0.9951856732368469,
      "center_x": 237.16666666666666,
      "center_y": 254.16666666666669,
      "distance_to_keypoint": 22.619388192924735
    }
  }
}